{
  "Mumbai": "12,442,373",
  "Delhi": "11,034,555",
  "Bangalore": "8,443,675",
  "Hyderabad": "6,731,790",
  "Ahmedabad": "5,577,940",
  "Chennai": "4,646,732",
  "Kolkata": "4,496,694",
  "Surat": "4,467,797",
  "Pune": "3,124,458",
  "Jaipur": "3,046,163",
  "Lucknow": "2,817,105",
  "Kanpur": "2,765,348",
  "Nagpur": "2,405,665",
  "Indore": "1,964,086",
  "Thane": "1,841,488",
  "Bhopal": "1,798,218",
  "Visakhapatnam[a][5]": "1,728,128",
  "Pimpri-Chinchwad": "1,727,692",
  "Patna": "1,684,222",
  "Vadodara": "1,670,806",
  "Ghaziabad": "1,648,643",
  "Ludhiana": "1,618,879",
  "Agra": "1,585,704",
  "Nashik": "1,486,053",
  "Faridabad": "1,414,050",
  "Meerut": "1,305,429",
  "Rajkot": "1,286,678",
  "Kalyan-Dombivali": "1,247,327",
  "Vasai-Virar": "1,222,390",
  "Varanasi": "1,198,491",
  "Srinagar": "1,180,570",
  "Aurangabad": "1,175,116",
  "Dhanbad": "1,162,472",
  "Amritsar": "1,132,383",
  "Navi": "Mumbai",
  "Allahabad": "1,112,544",
  "Howrah": "1,077,075",
  "Ranchi": "1,073,427",
  "Gwalior": "1,069,276",
  "Jabalpur": "1,055,525",
  "Vijayawada": "1,034,358",
  "Jodhpur": "1,033,918",
  "Madurai": "1,017,865",
  "Raipur": "1,010,087",
  "Kota[7]": "1,001,694",
  "Chandigarh": "961,587",
  "Guwahati": "957,352",
  "Solapur": "951,558",
  "Hubballi-Dharwad": "943,788",
  "Tiruchirappalli[8]": "916,674",
  "Bareilly": "898,167",
  "Mysore": "887,446",
  "Tiruppur": "877,778",
  "Gurgaon": "876,824",
  "Aligarh": "872,575",
  "Jalandhar": "862,196",
  "Bhubaneswar": "837,737",
  "Salem": "831,038",
  "Mira-Bhayandar": "814,655",
  "Warangal[9]": "811,844",
  "Thiruvananthapuram": "752,490",
  "Guntur[10]": "743,354",
  "Bhiwandi": "711,329",
  "Saharanpur": "703,345",
  "Gorakhpur": "671,048",
  "Bikaner": "647,804",
  "Amravati": "646,801",
  "Noida": "642,381",
  "Jamshedpur": "631,364",
  "Bhilai": "625,697",
  "Cuttack": "606,007",
  "Firozabad": "603,797",
  "Kochi": "601,574",
  "Nellore[11]": "600,869",
  "Bhavnagar": "593,768",
  "Dehradun": "578,420",
  "Durgapur": "566,937",
  "Asansol": "564,491",
  "Rourkela": "552,734",
  "Nanded": "550,564",
  "Kolhapur": "549,283",
  "Ajmer": "542,580",
  "Akola": "537,149",
  "Gulbarga": "532,031",
  "Jamnagar": "529,308",
  "Ujjain": "515,215",
  "Loni": "512,296",
  "Siliguri": "509,709",
  "Jhansi": "507,293",
  "Ulhasnagar": "506,937",
  "Jammu[12]": "503,690",
  "Sangli-Miraj": "&",
  "Mangalore": "499,486",
  "Erode[13]": "498,129",
  "Belgaum": "488,292",
  "Ambattur": "478,134",
  "Tirunelveli": "473,637",
  "Malegaon": "471,006",
  "Gaya": "463,454",
  "Jalgaon": "460,468",
  "Udaipur": "451,735",
  "Maheshtala": "449,423",
  "Davanagere": "435,128",
  "Kozhikode": "432,097",
  "Kurnool": "430,214",
  "Rajpur": "Sonarpur",
  "Rajahmundry[14][15]": "419,818",
  "Bokaro": "413,934",
  "South": "Dumdum",
  "Bellary": "409,644",
  "Patiala": "405,164",
  "Gopalpur": "404,991",
  "Agartala": "399,688",
  "Bhagalpur": "398,138",
  "Muzaffarnagar": "392,451",
  "Bhatpara": "390,467",
  "Panihati": "383,522",
  "Latur": "382,754",
  "Dhule": "376,093",
  "Tirupati[16]": "374,260",
  "Rohtak": "373,133",
  "Korba": "363,210",
  "Bhilwara": "360,009",
  "Berhampur": "355,823",
  "Muzaffarpur": "351,838",
  "Ahmednagar": "350,905",
  "Mathura": "349,336",
  "Kollam": "349,033",
  "Avadi": "344,701",
  "Kadapa": "343,054",
  "Kamarhati": "336,579",
  "Sambalpur": "335,761",
  "Bilaspur": "330,106",
  "Shahjahanpur": "327,975",
  "Satara": "326,789",
  "Bijapur": "326,360",
  "Rampur": "325,248",
  "Shivamogga": "322,428",
  "Chandrapur": "321,036",
  "Junagadh": "320,250",
  "Thrissur": "315,596",
  "Alwar": "315,310",
  "Bardhaman": "314,638",
  "Kulti": "313,977",
  "Kakinada": "325,985",
  "Nizamabad": "310,467",
  "Parbhani": "307,191",
  "Tumkur": "305,821",
  "Khammam": "305,000",
  "Ozhukarai": "300,028",
  "Bihar": "Sharif",
  "Panipat": "294,150",
  "Darbhanga": "294,116",
  "Bally": "291,972",
  "Aizawl": "291,822",
  "Dewas": "289,438",
  "Ichalkaranji": "287,570",
  "Karnal": "286,974",
  "Bathinda": "285,813",
  "Jalna": "285,349",
  "Eluru": "283,648[17]",
  "Kirari": "Suleman",
  "Barasat": "283,443",
  "Purnia": "280,547",
  "Satna": "280,248",
  "Mau": "279,060",
  "Sonipat": "277,053",
  "Farrukhabad": "275,750",
  "Sagar": "273,357",
  "Rourkela": "273,217",
  "Durg": "268,679",
  "Imphal": "264,986",
  "Ratlam": "264,810",
  "Hapur": "262,801",
  "Arrah": "261,099",
  "Karimnagar": "260,899",
  "Anantapur": "261,004",
  "Etawah": "256,838",
  "Ambernath": "254,003",
  "North": "Dumdum",
  "Bharatpur": "252,109",
  "Begusarai": "251,136",
  "New": "Delhi",
  "Gandhidham": "248,705",
  "Baranagar": "248,466",
  "Tiruvottiyur": "248,059",
  "Pondicherry": "241,773",
  "Sikar": "237,579",
  "Thoothukudi": "237,374",
  "Rewa": "235,422",
  "Mirzapur": "233,691",
  "Raichur": "232,456",
  "Pali": "229,956",
  "Ramagundam[20]": "229,644",
  "Haridwar": "228,832",
  "Vijayanagaram": "228,025",
  "Katihar": "225,982",
  "Nagercoil": "224,849",
  "Sri": "Ganganagar",
  "Karawal": "Nagar",
  "Mango": "223,805",
  "Thanjavur": "222,943",
  "Bulandshahr": "222,519",
  "Uluberia": "222,240",
  "Murwara": "221,883",
  "Sambhal": "220,813",
  "Singrauli": "220,257",
  "Nadiad": "218,095",
  "Secunderabad": "217,910",
  "Naihati": "217,900",
  "Yamunanagar": "216,677",
  "Bidhan": "Nagar",
  "Pallavaram": "215,417",
  "Bidar": "214,373",
  "Munger": "213,303",
  "Panchkula": "211,355",
  "Burhanpur": "210,886",
  "Raurkela": "Industrial",
  "Kharagpur": "207,604",
  "Dindigul": "207,327",
  "Gandhinagar": "206,167",
  "Hospet": "206,167",
  "Nangloi": "Jat",
  "English": "Bazar",
  "Ongole": "204,746",
  "Deoghar": "203,123",
  "Chapra": "202,352",
  "Haldia": "200,827",
  "Khandwa": "200,738",
  "Nandyal": "200,516",
  "Morena": "200,482",
  "Amroha": "198,471",
  "Anand": "198,282",
  "Bhind": "197,585",
  "Bhalswa": "Jahangir",
  "Madhyamgram": "196,127",
  "Bhiwani": "196,057",
  "Navi": "Mumbai",
  "Baharampur": "195,223",
  "Ambala": "195,153",
  "Morbi": "194,947",
  "Fatehpur": "193,193",
  "Rae": "Bareli",
  "Mahaboobnagar": "190,400",
  "Bhusawal": "187,421",
  "Orai": "187,137",
  "Bahraich": "186,223",
  "Vellore": "185,803",
  "Mahesana": "184,991",
  "Sambalpur": "184,000",
  "Raiganj": "183,612",
  "Sirsa": "182,534",
  "Danapur": "182,429",
  "Serampore": "181,842",
  "Sultan": "Pur",
  "Guna": "180,935",
  "Jaunpur": "180,362",
  "Panvel": "180,020",
  "Shivpuri": "179,977",
  "Surendranagar": "Dudhrej",
  "Unnao": "177,658",
  "Hugli": "and",
  "Alappuzha": "174,164",
  "Kottayam": "172,878",
  "Machilipatnam": "169,892",
  "Shimla": "169,578",
  "Adoni": "166,537",
  "Udupi": "165,401",
  "Tenali": "164,937",
  "Proddatur": "163,600",
  "Saharsa": "155,175",
  "Hindupur": "151,835",
  "Sasaram": "147,396",
  "Hajipur": "147,126",
  "Bhimavaram": "142,280",
  "Kumbakonam": "140,056",
  "Dehri": "137,068",
  "Madanapalle": "135,669",
  "Siwan": "134,458",
  "Bettiah": "132,896",
  "Guntakal": "126,270",
  "Srikakulam": "125,939",
  "Motihari": "125,183",
  "Dharmavaram": "121,874",
  "Gudivada": "118,167",
  "Phagwara": "117,966",
  "Narasaraopet": "116,250",
  "Suryapet": "115,250",
  "Siddipet": "114,000",
  "Tadipatri": "108,171",
  "Kishanganj": "107,076",
  "Karaikudi": "106,714",
  "Miryalaguda": "109,891",
  "Jamalpur": "105,221",
  "Kavali": "104,000",
  "Tadepalligudem": "103,906",
  "Amaravati": "103,000",
  "Buxar": "102,591",
  "Jehanabad": "102,456",
  "Aurangabad": "101,520"
}
"Mumbai":"12,442,373",
"Delhi":"11,034,555",
"Bangalore":"8,443,675",
"Hyderabad":"6,731,790",
"Ahmedabad":"5,577,940",
"Chennai":"4,646,732",
"Kolkata":"4,496,694",
"Surat":"4,467,797",
"Pune":"3,124,458",
"Jaipur":"3,046,163",
"Lucknow":"2,817,105",
"Kanpur":"2,765,348",
"Nagpur":"2,405,665",
"Indore":"1,964,086",
"Thane":"1,841,488",
"Bhopal":"1,798,218",
"Visakhapatnam[a][5]":"1,728,128",
"Pimpri-Chinchwad":"1,727,692",
"Patna":"1,684,222",
"Vadodara":"1,670,806",
"Ghaziabad":"1,648,643",
"Ludhiana":"1,618,879",
"Agra":"1,585,704",
"Nashik":"1,486,053",
"Faridabad":"1,414,050",
"Meerut":"1,305,429",
"Rajkot":"1,286,678",
"Kalyan-Dombivali":"1,247,327",
"Vasai-Virar":"1,222,390",
"Varanasi":"1,198,491",
"Srinagar":"1,180,570",
"Aurangabad":"1,175,116",
"Dhanbad":"1,162,472",
"Amritsar":"1,132,383",
"Navi":"Mumbai",
"Allahabad":"1,112,544",
"Howrah":"1,077,075",
"Ranchi":"1,073,427",
"Gwalior":"1,069,276",
"Jabalpur":"1,055,525",
"Vijayawada":"1,034,358",
"Jodhpur":"1,033,918",
"Madurai":"1,017,865",
"Raipur":"1,010,087",
"Kota[7]":"1,001,694",
"Chandigarh":"961,587",
"Guwahati":"957,352",
"Solapur":"951,558",
"Hubballi-Dharwad":"943,788",
"Tiruchirappalli[8]":"916,674",
"Bareilly":"898,167",
"Mysore":"887,446",
"Tiruppur":"877,778",
"Gurgaon":"876,824",
"Aligarh":"872,575",
"Jalandhar":"862,196",
"Bhubaneswar":"837,737",
"Salem":"831,038",
"Mira-Bhayandar":"814,655",
"Warangal[9]":"811,844",
"Thiruvananthapuram":"752,490",
"Guntur[10]":"743,354",
"Bhiwandi":"711,329",
"Saharanpur":"703,345",
"Gorakhpur":"671,048",
"Bikaner":"647,804",
"Amravati":"646,801",
"Noida":"642,381",
"Jamshedpur":"631,364",
"Bhilai":"625,697",
"Cuttack":"606,007",
"Firozabad":"603,797",
"Kochi":"601,574",
"Nellore[11]":"600,869",
"Bhavnagar":"593,768",
"Dehradun":"578,420",
"Durgapur":"566,937",
"Asansol":"564,491",
"Rourkela":"552,734",
"Nanded":"550,564",
"Kolhapur":"549,283",
"Ajmer":"542,580",
"Akola":"537,149",
"Gulbarga":"532,031",
"Jamnagar":"529,308",
"Ujjain":"515,215",
"Loni":"512,296",
"Siliguri":"509,709",
"Jhansi":"507,293",
"Ulhasnagar":"506,937",
"Jammu[12]":"503,690",
"Sangli-Miraj":"&",
"Mangalore":"499,486",
"Erode[13]":"498,129",
"Belgaum":"488,292",
"Ambattur":"478,134",
"Tirunelveli":"473,637",
"Malegaon":"471,006",
"Gaya":"463,454",
"Jalgaon":"460,468",
"Udaipur":"451,735",
"Maheshtala":"449,423",
"Davanagere":"435,128",
"Kozhikode":"432,097",
"Kurnool":"430,214",
"Rajpur":"Sonarpur",
"Rajahmundry[14][15]":"419,818",
"Bokaro":"413,934",
"South":"Dumdum",
"Bellary":"409,644",
"Patiala":"405,164",
"Gopalpur":"404,991",
"Agartala":"399,688",
"Bhagalpur":"398,138",
"Muzaffarnagar":"392,451",
"Bhatpara":"390,467",
"Panihati":"383,522",
"Latur":"382,754",
"Dhule":"376,093",
"Tirupati[16]":"374,260",
"Rohtak":"373,133",
"Korba":"363,210",
"Bhilwara":"360,009",
"Berhampur":"355,823",
"Muzaffarpur":"351,838",
"Ahmednagar":"350,905",
"Mathura":"349,336",
"Kollam":"349,033",
"Avadi":"344,701",
"Kadapa":"343,054",
"Kamarhati":"336,579",
"Sambalpur":"335,761",
"Bilaspur":"330,106",
"Shahjahanpur":"327,975",
"Satara":"326,789",
"Bijapur":"326,360",
"Rampur":"325,248",
"Shivamogga":"322,428",
"Chandrapur":"321,036",
"Junagadh":"320,250",
"Thrissur":"315,596",
"Alwar":"315,310",
"Bardhaman":"314,638",
"Kulti":"313,977",
"Kakinada":"325,985",
"Nizamabad":"310,467",
"Parbhani":"307,191",
"Tumkur":"305,821",
"Khammam":"305,000",
"Ozhukarai":"300,028",
"Bihar":"Sharif",
"Panipat":"294,150",
"Darbhanga":"294,116",
"Bally":"291,972",
"Aizawl":"291,822",
"Dewas":"289,438",
"Ichalkaranji":"287,570",
"Karnal":"286,974",
"Bathinda":"285,813",
"Jalna":"285,349",
"Eluru":"283,648[17]",
"Kirari":"Suleman",
"Barasat":"283,443",
"Purnia":"280,547",
"Satna":"280,248",
"Mau":"279,060",
"Sonipat":"277,053",
"Farrukhabad":"275,750",
"Sagar":"273,357",
"Rourkela":"273,217",
"Durg":"268,679",
"Imphal":"264,986",
"Ratlam":"264,810",
"Hapur":"262,801",
"Arrah":"261,099",
"Karimnagar":"260,899",
"Anantapur":"261,004",
"Etawah":"256,838",
"Ambernath":"254,003",
"North":"Dumdum",
"Bharatpur":"252,109",
"Begusarai":"251,136",
"New":"Delhi",
"Gandhidham":"248,705",
"Baranagar":"248,466",
"Tiruvottiyur":"248,059",
"Pondicherry":"241,773",
"Sikar":"237,579",
"Thoothukudi":"237,374",
"Rewa":"235,422",
"Mirzapur":"233,691",
"Raichur":"232,456",
"Pali":"229,956",
"Ramagundam[20]":"229,644",
"Haridwar":"228,832",
"Vijayanagaram":"228,025",
"Katihar":"225,982",
"Nagercoil":"224,849",
"Sri":"Ganganagar",
"Karawal":"Nagar",
"Mango":"223,805",
"Thanjavur":"222,943",
"Bulandshahr":"222,519",
"Uluberia":"222,240",
"Murwara":"221,883",
"Sambhal":"220,813",
"Singrauli":"220,257",
"Nadiad":"218,095",
"Secunderabad":"217,910",
"Naihati":"217,900",
"Yamunanagar":"216,677",
"Bidhan":"Nagar",
"Pallavaram":"215,417",
"Bidar":"214,373",
"Munger":"213,303",
"Panchkula":"211,355",
"Burhanpur":"210,886",
"Raurkela":"Industrial",
"Kharagpur":"207,604",
"Dindigul":"207,327",
"Gandhinagar":"206,167",
"Hospet":"206,167",
"Nangloi":"Jat",
"English":"Bazar",
"Ongole":"204,746",
"Deoghar":"203,123",
"Chapra":"202,352",
"Haldia":"200,827",
"Khandwa":"200,738",
"Nandyal":"200,516",
"Morena":"200,482",
"Amroha":"198,471",
"Anand":"198,282",
"Bhind":"197,585",
"Bhalswa":"Jahangir",
"Madhyamgram":"196,127",
"Bhiwani":"196,057",
"Navi":"Mumbai",
"Baharampur":"195,223",
"Ambala":"195,153",
"Morbi":"194,947",
"Fatehpur":"193,193",
"Rae":"Bareli",
"Mahaboobnagar":"190,400",
"Bhusawal":"187,421",
"Orai":"187,137",
"Bahraich":"186,223",
"Vellore":"185,803",
"Mahesana":"184,991",
"Sambalpur":"184,000",
"Raiganj":"183,612",
"Sirsa":"182,534",
"Danapur":"182,429",
"Serampore":"181,842",
"Sultan":"Pur",
"Guna":"180,935",
"Jaunpur":"180,362",
"Panvel":"180,020",
"Shivpuri":"179,977",
"Surendranagar":"Dudhrej",
"Unnao":"177,658",
"Hugli":"and",
"Alappuzha":"174,164",
"Kottayam":"172,878",
"Machilipatnam":"169,892",
"Shimla":"169,578",
"Adoni":"166,537",
"Udupi":"165,401",
"Tenali":"164,937",
"Proddatur":"163,600",
"Saharsa":"155,175",
"Hindupur":"151,835",
"Sasaram":"147,396",
"Hajipur":"147,126",
"Bhimavaram":"142,280",
"Kumbakonam":"140,056",
"Dehri":"137,068",
"Madanapalle":"135,669",
"Siwan":"134,458",
"Bettiah":"132,896",
"Guntakal":"126,270",
"Srikakulam":"125,939",
"Motihari":"125,183",
"Dharmavaram":"121,874",
"Gudivada":"118,167",
"Phagwara":"117,966",
"Narasaraopet":"116,250",
"Suryapet":"115,250",
"Siddipet":"114,000",
"Tadipatri":"108,171",
"Kishanganj":"107,076",
"Karaikudi":"106,714",
"Miryalaguda":"109,891",
"Jamalpur":"105,221",
"Kavali":"104,000",
"Tadepalligudem":"103,906",
"Amaravati":"103,000",
"Buxar":"102,591",
"Jehanabad":"102,456",
"Aurangabad":"101,520",
